Workbook
Name CategoryList: 'Client Setup'!$A$23:$A$33
Name CategoryTable: 'Client Setup'!$A$23:$B$33
Name DestinationList: 'Client Setup'!$I$61:$I$71
Name DriveRoutes: 'Client Setup'!$A$57:$B$65
Name FlightTypes: 'Client Setup'!$A$75:$C$77
Name HotelRates: 'Client Setup'!$A$82:$C$90
Name LocationList: 'Client Setup'!$A$124:$A$145
Name OriginList: 'Client Setup'!$I$53:$I$58
Name PerDiemRates: 'Client Setup'!$A$94:$C$95
Name TrainRoutes: 'Client Setup'!$A$69:$C$71
Name VehicleRates: 'Client Setup'!$A$105:$G$114

Sheet Client Setup
A2: Client Setup — Complete Once Per Program | H2: Color | I2: Meaning
I3: Dropdown — click to select
A4: EVENT DETAILS | I4: Manual entry or formula
A5: Client Name: | B5: Alex Stack
A6: Event Date: | B6: 46396
A7: Guest Count: | B7: 60
A8: Service Style: | B8: Family Style
A9: Alcohol: | B9: Full Bar
A10: Event Time: | B10: 6-9
A11: Company Name: | B11: QCED
A12: Program Name: | B12: Sample Program
A13: Client Hotel:
A15: LOCATION & TAX RATES
A16: State / Location: | B16: Wilson NC | D16: Tax rates auto-populate from location
A17: Food Tax Rate: | B17: =IF(B16="","",VLOOKUP(B16,$A$124:$D$145,2,FALSE)) | D17: Tax on food & NA beverages
A18: Alcohol Tax Rate: | B18: =IF(B16="","",VLOOKUP(B16,$A$124:$D$145,3,FALSE)) | D18: Tax on bar/alcohol
A19: General Sales Tax Rate: | B19: =IF(B16="","",VLOOKUP(B16,$A$124:$D$145,4,FALSE)) | D19: Tax on equipment, rentals, staffing
A21: PRICING & COMMISSION
A22: Category | B22: Markup % | C22: Note
A23: Catering & F&B | B23: 0.54 | C23: Floor — clients compare per-head pricing
A24: Venues & Room Rentals | B24: 0.6 | C24: Full venue relationship management
A25: AV & Production | B25: 0.65 | C25: Technical coordination, hard to price-shop
A26: Décor & Design | B26: 0.85 | C26: Custom creative — no comparison exists
A27: Entertainment | B27: 0.75 | C27: Talent sourcing, contracts, riders
A28: Activities & Experiences | B28: 0.75 | C28: Curation, coordination, permitting
A29: Transportation | B29: 0.75 | C29: Route planning, high-liability
A30: Staffing & Labor | B30: 0.9 | C30: Recruitment, scheduling, management
A31: Purchased / Sourced Items | B31: 2 | C31: Small items, disproportionate time (3×)
A32: Delivery & Logistics | B32: 0.85 | C32: Timing risk, damage liability
A33: Tours & Guided Experiences | B33: 0.65 | C33: Guide sourcing, route design
A34: Absolute Floor: 54% | C34: No exceptions without owner approval
A35: CC Processing Fee %: | C35: 0.035 | D35: Applied to subtotal
A36: Third-Party Commission: | C36: 0.05 | D36: Select commission rate
A37: Global DMC (6.5%): | C37: Yes | D37: Yes = 6.5% applied
A39: RESTAURANT FEE DEFAULTS (can be overridden per venue)
A40: Service Charge: | C40: 20% | D40: 20%, 21.5%, or None
A41: Gratuity: | C41: 20% | D41: 20% or None
A42: Admin Fee: | C42: 5% | D42: 5% or None
A44: HOW TO USE
A45: 1. Fill out all fields above — this information feeds into every estimate tab.
A46: 2. Right-click the 'Venue Estimate' tab → 'Move or Copy' → check 'Create a copy'.
A47: 3. Rename the copied tab to the restaurant/venue name.
A48: 4. On the new tab, enter venue name, F&B minimum, and line item pricing.
A49: 5. Fee structure defaults from this tab but can be overridden per venue (yellow fields).
A50: 6. The Client-Ready Table auto-generates rounded numbers for Canva export.
A52: QC TRAVEL RATE TABLES | I52: Origins
I53: Charlotte
A54: TRANSPORTATION RATES | I54: DC
A55: Drive Costs (round trip per trip, based on $0.725/mile + parking/tolls) | I55: Philadelphia
A56: Route | B56: Cost | I56: NYC
A57: DC to Richmond VA | B57: 205 | I57: Atlanta
A58: Charlotte to Raleigh NC | B58: 230 | I58: Other
A59: Charlotte to Asheville NC | B59: 190
A60: Charlotte to Charleston SC | B60: 300 | I60: Destinations
A61: Charlotte to Atlanta | B61: 360 | I61: NYC
A62: DC to Virginia Secondary | B62: 215 | I62: DC
A63: DC to Philadelphia | B63: 190 | I63: Philadelphia
A64: DC to NYC | B64: 325 | I64: Charlotte
A65: Charlotte to DC | B65: 270 | I65: Atlanta
I66: Richmond VA
A67: Train Costs (round trip, per person) | I67: Charleston SC
A68: Route | B68: Low | C68: High | I68: Raleigh NC
A69: DC to NYC | B69: 180 | C69: 300 | I69: Asheville NC
A70: Philadelphia to NYC | B70: 120 | C70: 220 | I70: Virginia Secondary
A71: DC to Philadelphia | B71: 120 | C71: 200 | I71: Other
A73: Flight Costs (round trip, per person)
A74: Route Type | B74: Low | C74: High
A75: Short Haul | B75: 300 | C75: 450
A76: Medium Haul | B76: 400 | C76: 600
A77: Major Market to NYC | B77: 450 | C77: 650
A78: Last Minute Booking Buffer: +$150 per person
A80: HOTEL RATES (Per Night, Per Person)
A81: Market | B81: Low | C81: High
A82: NYC | B82: 450 | C82: 650
A83: DC | B83: 350 | C83: 550
A84: Charleston SC | B84: 350 | C84: 550
A85: Atlanta | B85: 275 | C85: 450
A86: Charlotte | B86: 250 | C86: 400
A87: Asheville NC | B87: 300 | C87: 500
A88: Raleigh NC | B88: 250 | C88: 400
A89: Philadelphia | B89: 350 | C89: 550
A90: Virginia Secondary | B90: 200 | C90: 350
A92: PER DIEM RATES
A93: Market | B93: Full Day | C93: Half Day | D93: Notes
A94: Standard (all except NYC) | B94: 68 | C94: 34 | D94: Full = breakfast, lunch, dinner. Half = dinner only
A95: NYC | B95: 92 | C95: 46 | D95: Full = breakfast, lunch, dinner. Half = dinner only
A97: Per Diem by Trip Length (auto-calculated reference)
A98: Trip Length | B98: Calculation | C98: Standard Total | D98: NYC Total
A99: 1 Night | B99: Half + Full | C99: =C94+B94 | D99: =C95+B95
A100: 2 Nights | B100: Half + Full + Half | C100: =2*C94+B94 | D100: =2*C95+B95
A101: 3 Nights | B101: Half + 2 Full + Half | C101: =2*C94+2*B94 | D101: =2*C95+2*B95
A103: SITE VISIT VEHICLE RATES
A104: Market | B104: Sedan Hourly | C104: Sedan Airport Transfer | D104: SUV Hourly | E104: SUV Airport Transfer | F104: Sprinter Hourly | G104: Sprinter Airport Transfer
A105: NYC | B105: 85 | C105: 250 | D105: 125 | E105: 350 | F105: 175 | G105: 500
A106: DC | B106: 75 | C106: 200 | D106: 100 | E106: 275 | F106: 150 | G106: 400
A107: Philadelphia | B107: 70 | C107: 175 | D107: 95 | E107: 250 | F107: 140 | G107: 375
A108: Charlotte | B108: 60 | C108: 150 | D108: 85 | E108: 200 | F108: 125 | G108: 325
A109: Raleigh NC | B109: 60 | C109: 150 | D109: 85 | E109: 200 | F109: 125 | G109: 325
A110: Asheville NC | B110: 65 | C110: 175 | D110: 90 | E110: 225 | F110: 130 | G110: 350
A111: Charleston SC | B111: 60 | C111: 150 | D111: 85 | E111: 200 | F111: 125 | G111: 325
...

Sheet Venue Estimate
A2: Restaurant / Venue Estimate | H2: Color | I2: Meaning
I3: Dropdown — click to select
A4: VENUE DETAILS | I4: Manual entry or formula
A5: Venue / Restaurant Name: | I5: Copy & paste into Canva
A6: Room / Space:
A7: F&B Minimum: | I7: PRIVATE DINING ESTIMATE
A8: Is Venue Rental Taxable? | B8: Yes | I8: ='Client Setup'!B5 | K8: =B5
A9: Client: | B9: ='Client Setup'!B5 | I9: =TEXT('Client Setup'!B6,"MMMM D, YYYY") | K9: ='Client Setup'!B7&" Guests"
A10: Guest Count: | B10: ='Client Setup'!B7
A11: Location: | B11: ='Client Setup'!B16 | I11: Item | J11: Amount | K11: PP Price
A12: Company: | B12: ='Client Setup'!B11
A13: Program: | B13: ='Client Setup'!B12
A14: Client Hotel: | B14: ='Client Setup'!B13
A15: Event Time: | B15: ='Client Setup'!B10 | I15: Menu | J15: =ROUNDUP((E24+E26)/50,0)*50 | K15: =IF('Client Setup'!B7>0,CEILING(J12/'Client Setup'!B7,1),0)
A16: VENUE FEE OVERRIDES (defaults from Client Setup — change yellow fields to override) | I16: Bar Package | J16: =ROUNDUP(E25/50,0)*50 | K16: =IF('Client Setup'!B7>0,CEILING(J13/'Client Setup'!B7,1),0)
A17: Service Charge: | C17: ='Client Setup'!C40 | D17: 20%, 21.5%, or None | I17: Staffing | J17: =ROUNDUP((E28+SUM(E38:E40))/50,0)*50 | K17: =IF('Client Setup'!B7>0,CEILING(J14/'Client Setup'!B7,1),0)
A18: Gratuity: | C18: ='Client Setup'!C41 | D18: 20% or None | I18: Equipment | J18: =ROUNDUP((E29+E30+E31)/50,0)*50 | K18: =IF('Client Setup'!B7>0,CEILING(J15/'Client Setup'!B7,1),0)
A19: Admin Fee: | C19: ='Client Setup'!C42 | D19: 5% or None | I19: Venue Rental | J19: =ROUNDUP((E33+E34+E35)/50,0)*50 | K19: =IF('Client Setup'!B7>0,CEILING(J16/'Client Setup'!B7,1),0)
I20: Production Fee | J20: =ROUNDUP((E51+E52+E53+E55+E56)/100,0)*100 | K20: =IF('Client Setup'!B7>0,CEILING(J17/'Client Setup'!B7,1),0)
A21: COST BUILD | I21: Tax | J21: =ROUNDUP((E44+E45+E47+E50)/50,0)*50 | K21: =IF('Client Setup'!B7>0,CEILING(J18/'Client Setup'!B7,1),0)
A22: Line Item | B22: Qty | C22: Unit Price | D22: Our Cost | E22: Client Cost | F22: Tax Rate | G22: Category
A23: FOOD & BEVERAGE (F&B Tax Applied) | I23: TOTAL ESTIMATE | J23: =SUM(J12:J18) | K23: =IF('Client Setup'!B7>0,CEILING(J20/'Client Setup'!B7,1),0)
A24: Per Person Food | B24: ='Client Setup'!B7 | D24: =B24*C24 | E24: =IFERROR(D24*(1+VLOOKUP(G24,CategoryTable,2,FALSE)),0) | F24: ='Client Setup'!B17 | G24: Catering & F&B | I24: Guest Count | J24: ='Client Setup'!B7
A25: Bar Package | B25: ='Client Setup'!B7 | D25: =B25*C25 | E25: =IFERROR(D25*(1+VLOOKUP(G25,CategoryTable,2,FALSE)),0) | F25: ='Client Setup'!B18 | G25: Catering & F&B
A26: NA Beverages | B26: ='Client Setup'!B7 | D26: =B26*C26 | E26: =IFERROR(D26*(1+VLOOKUP(G26,CategoryTable,2,FALSE)),0) | F26: ='Client Setup'!B17 | G26: Catering & F&B
A27: TAXABLE EQUIPMENT, RENTALS & STAFFING (General Sales Tax) | I27: TEAM NOTES
A28: Staffing | B28: 1 | D28: =B28*C28 | E28: =IFERROR(D28*(1+VLOOKUP(G28,CategoryTable,2,FALSE)),0) | F28: ='Client Setup'!B19 | G28: Staffing & Labor | I28: Venue Contact:
A29: Catering Equipment | B29: 1 | D29: =B29*C29 | E29: =IFERROR(D29*(1+VLOOKUP(G29,CategoryTable,2,FALSE)),0) | F29: ='Client Setup'!B19 | G29: AV & Production
A30: Rental Equipment | B30: 1 | D30: =B30*C30 | E30: =IFERROR(D30*(1+VLOOKUP(G30,CategoryTable,2,FALSE)),0) | F30: ='Client Setup'!B19 | G30: Décor & Design | I30: Menu Notes:
A31: Additional Equipment | B31: 1 | D31: =B31*C31 | E31: =IFERROR(D31*(1+VLOOKUP(G31,CategoryTable,2,FALSE)),0) | F31: ='Client Setup'!B19 | G31: AV & Production
A32: VENUE FEES (Taxable if toggled above)
A33: Venue / Room Rental | B33: 1 | D33: =B33*C33 | E33: =IFERROR(D33*(1+VLOOKUP(G33,CategoryTable,2,FALSE)),0) | F33: =IF(B8="Yes",'Client Setup'!B19,0) | G33: Venues & Room Rentals | I33: Logistics:
A34: Additional Venue Space | B34: 1 | D34: =B34*C34 | E34: =IFERROR(D34*(1+VLOOKUP(G34,CategoryTable,2,FALSE)),0) | F34: =IF(B8="Yes",'Client Setup'!B19,0) | G34: Venues & Room Rentals
A35: Additional Services | B35: 1 | D35: =B35*C35 | E35: =IFERROR(D35*(1+VLOOKUP(G35,CategoryTable,2,FALSE)),0) | F35: =IF(B8="Yes",'Client Setup'!B19,0) | G35: Venues & Room Rentals | I35: Additional Notes:
A37: NON-TAXABLE QC STAFFING
A38: QC Event Staff | B38: =IF('Client Setup'!B7>100,3,IF('Client Setup'!B7>50,2,1)) | C38: 500 | D38: =B38*C38 | E38: =IFERROR(D38*(1+VLOOKUP(G38,CategoryTable,2,FALSE)),0) | F38: 0 | G38: Staffing & Labor
D39: =B39*C39 | E39: =IFERROR(D39*(1+VLOOKUP(G39,CategoryTable,2,FALSE)),0) | F39: 0 | G39: Staffing & Labor
D40: =B40*C40 | E40: =IFERROR(D40*(1+VLOOKUP(G40,CategoryTable,2,FALSE)),0) | F40: 0 | G40: Staffing & Labor
A42: ESTIMATE SUMMARY
A43: F&B Subtotal | D43: =SUM(D24:D26) | E43: =SUM(E24:E26)
A44: Food Tax | D44: =IFERROR(D24*F24+D26*F26,0) | E44: =IFERROR(E24*F24+E26*F26,0)
A45: Alcohol Tax | D45: =IFERROR(D25*F25,0) | E45: =IFERROR(E25*F25,0)
A46: Equipment & Staffing Subtotal | D46: =SUM(D28:D31) | E46: =SUM(E28:E31)
A47: Equipment & Staffing Tax | D47: =IFERROR(D46*F28,0) | E47: =IFERROR(E46*F28,0)
A48: QC Staffing Subtotal | D48: =SUM(D38:D40) | E48: =SUM(E38:E40)
A49: Venue Fees Subtotal | D49: =SUM(D33:D35) | E49: =SUM(E33:E35)
A50: Venue Tax | D50: =IFERROR(D49*F33,0) | E50: =IFERROR(E49*F33,0)
A51: Service Charge | D51: =D43*IF(C17="20%",0.2,IF(C17="21.5%",0.215,0)) | E51: =E43*IF(C17="20%",0.2,IF(C17="21.5%",0.215,0))
A52: Gratuity | D52: =D43*IF(C18="20%",0.2,0) | E52: =E43*IF(C18="20%",0.2,0)
A53: Admin Fee | D53: =D43*IF(C19="5%",0.05,0) | E53: =E43*IF(C19="5%",0.05,0)
A54: SUBTOTAL | D54: =SUM(D43:D53) | E54: =SUM(E43:E53)
A55: CC Processing Fee | D55: =E55 | E55: =IFERROR(E54*'Client Setup'!C35,0)
A56: Third-Party Commission | D56: =E56 | E56: =IFERROR((E43+E46+E48+E49+E51+E52+E53)*'Client Setup'!C36,0)
A57: TOTAL ESTIMATE | D57: =D54+D55+D56 | E57: =E54+E55+E56
A59: CLIENT PRICING
A60: Price Per Person | B60: =IF('Client Setup'!B7>0,CEILING(E57/'Client Setup'!B7,1),0)
A61: Total Estimated Client Cost | B61: =IF('Client Setup'!B7>0,B60*'Client Setup'!B7,0)
A62: F&B Minimum Status: | B62: =IF(B7=0,"No F&B Minimum Set",IF(E43>=B7,"✓ F&B MINIMUM MET","✗ NOT MET — Shortfall: "&TEXT(B7-E43,"$#,##0")))
A65: QC TRAVEL EXPENSES | B65: Trip 1 | C65: Trip 2 | D65: Trip 3
A66: Trip Label
A67: Origin | B67: DC
A68: Destination | B68: NYC
A69: Travel Type | B69: Train
A70: Flight Type
A71: Last Minute Buffer
A72: Staff Traveling | B72: 1
A73: Nights | B73: 2
A74: Hotel Budget | B74: Low
A75: Vehicle Type
A76: Vehicle Service
A77: Vehicle Hours
A78: Custom Vehicle Cost
A80: Travel Cost | B80: =IF(OR(B68="",B72=""),0,IF(B69="Drive",IFERROR(VLOOKUP(B67&" to "&B68,DriveRoutes,2,FALSE),0),IF(B69="Train",IFERROR(VLOOKUP(B67&" to "&B68,TrainRoutes,2,FALSE),0)*B72,IF(B69="Flight",IFERROR(VLOOKUP(B70,FlightTypes,2,FALSE),0)*B72+IF(B71="Yes",150*B72,0),0)))) | C80: =IF(OR(C68="",C72=""),0,IF(C69="Drive",IFERROR(VLOOKUP(C67&" to "&C68,DriveRoutes,2,FALSE),0),IF(C69="Train",IFERROR(VLOOKUP(C67&" to "&C68,TrainRoutes,2,FALSE),0)*C72,IF(C69="Flight",IFERROR(VLOOKUP(C70,FlightTypes,2,FALSE),0)*C72+IF(C71="Yes",150*C72,0),0)))) | D80: =IF(OR(D68="",D72=""),0,IF(D69="Drive",IFERROR(VLOOKUP(D67&" to "&D68,DriveRoutes,2,FALSE),0),IF(D69="Train",IFERROR(VLOOKUP(D67&" to "&D68,TrainRoutes,2,FALSE),0)*D72,IF(D69="Flight",IFERROR(VLOOKUP(D70,FlightTypes,2,FALSE),0)*D72+IF(D71="Yes",150*D72,0),0))))
A81: Hotel Cost | B81: =IF(OR(B68="",B72="",B73=""),0,B73*IFERROR(IF(B74="High",VLOOKUP(B68,HotelRates,3,FALSE),VLOOKUP(B68,HotelRates,2,FALSE)),0)*B72) | C81: =IF(OR(C68="",C72="",C73=""),0,C73*IFERROR(IF(C74="High",VLOOKUP(C68,HotelRates,3,FALSE),VLOOKUP(C68,HotelRates,2,FALSE)),0)*C72) | D81: =IF(OR(D68="",D72="",D73=""),0,D73*IFERROR(IF(D74="High",VLOOKUP(D68,HotelRates,3,FALSE),VLOOKUP(D68,HotelRates,2,FALSE)),0)*D72)
A82: Per Diem Cost | B82: =IF(OR(B68="",B72=""),0,IF(B68="NYC",IF(B73=0,'Client Setup'!C95,IF(B73=1,'Client Setup'!C95+'Client Setup'!B95,2*'Client Setup'!C95+(B73-1)*'Client Setup'!B95)),IF(B73=0,'Client Setup'!C94,IF(B73=1,'Client Setup'!C94+'Client Setup'!B94,2*'Client Setup'!C94+(B73-1)*'Client Setup'!B94)))*B72) | C82: =IF(OR(C68="",C72=""),0,IF(C68="NYC",IF(C73=0,'Client Setup'!C95,IF(C73=1,'Client Setup'!C95+'Client Setup'!B95,2*'Client Setup'!C95+(C73-1)*'Client Setup'!B95)),IF(C73=0,'Client Setup'!C94,IF(C73=1,'Client Setup'!C94+'Client Setup'!B94,2*'Client Setup'!C94+(C73-1)*'Client Setup'!B94)))*C72) | D82: =IF(OR(D68="",D72=""),0,IF(D68="NYC",IF(D73=0,'Client Setup'!C95,IF(D73=1,'Client Setup'!C95+'Client Setup'!B95,2*'Client Setup'!C95+(D73-1)*'Client Setup'!B95)),IF(D73=0,'Client Setup'!C94,IF(D73=1,'Client Setup'!C94+'Client Setup'!B94,2*'Client Setup'!C94+(D73-1)*'Client Setup'!B94)))*D72)
A83: Vehicle Cost | B83: =IF(AND(ISNUMBER(B78),B78>0),B78,IF(OR(B75="",B75="None"),0,IF(B76="Airport Transfer",IFERROR(VLOOKUP(B68,VehicleRates,IF(B75="Sedan",3,IF(B75="SUV",5,7)),FALSE),0),IF(B76="Hourly",IFERROR(VLOOKUP(B68,VehicleRates,IF(B75="Sedan",2,IF(B75="SUV",4,6)),FALSE),0)*B77,0)))) | C83: =IF(AND(ISNUMBER(C78),C78>0),C78,IF(OR(C75="",C75="None"),0,IF(C76="Airport Transfer",IFERROR(VLOOKUP(C68,VehicleRates,IF(C75="Sedan",3,IF(C75="SUV",5,7)),FALSE),0),IF(C76="Hourly",IFERROR(VLOOKUP(C68,VehicleRates,IF(C75="Sedan",2,IF(C75="SUV",4,6)),FALSE),0)*C77,0)))) | D83: =IF(AND(ISNUMBER(D78),D78>0),D78,IF(OR(D75="",D75="None"),0,IF(D76="Airport Transfer",IFERROR(VLOOKUP(D68,VehicleRates,IF(D75="Sedan",3,IF(D75="SUV",5,7)),FALSE),0),IF(D76="Hourly",IFERROR(VLOOKUP(D68,VehicleRates,IF(D75="Sedan",2,IF(D75="SUV",4,6)),FALSE),0)*D77,0))))
A84: Trip Total | B84: =B80+B81+B82+B83 | C84: =C80+C81+C82+C83 | D84: =D80+D81+D82+D83
A86: Total Travel Expenses | D86: =B84+C84+D84
A88: PROFIT & MARGIN ANALYSIS
A89: Third-Party Commission | C89: ='Client Setup'!C36 | D89: =(E43+E46+E48+E49+E51+E52+E53)*C83
A90: Global DMC Fee (6.5%) | C90: =IF('Client Setup'!C37="Yes",0.065,0) | D90: =IF('Client Setup'!C37="Yes",(E43+E46+E48+E49+E51+E52+E53)*0.065,0)
A91: Total Vendor Costs (incl. CC fee) | D91: =D54+D55
A92: QC Revenue | D92: =IFERROR(E57-D83-D84-D85,0)
A93: QC Margin % | D93: =IFERROR(IF(E57>0,D86/E57,0),0)
A94: Margin Health | D94: =IF(D87>=0.45,"✓ STRONG",IF(D87>=0.35,"→ ON TARGET",IF(D87>=0.25,"⚠ REVIEW","✗ BELOW FLOOR")))
A96: Estimated Team Hours | D96: =IF(ISNUMBER(C90),C90*90,0) | E96: Hours × $90/hr
A97: True Net Profit | D97: =D92-D96-D86
A98: True Net Margin % | D98: =IFERROR(IF(E57>0,D91/E57,0),0)
A99: True Net Health | D99: =IF(D92>=0.15,"✓ STRONG",IF(D92>=0.07,"→ ON TARGET",IF(D92>=0,"⚠ THIN","✗ LOSING MONEY")))

Sheet Decor Estimate
A2: Decor & Production Estimate
A4: EVENT INFO (from Client Setup) | J4: DETAILED CLIENT VIEW | M4: SUMMARY VIEW
A5: Client: | B5: ='Client Setup'!B5 | J5: Itemized — each section is one Canva slide | M5: Category totals for client
A6: Event Date: | B6: ='Client Setup'!B6
A7: Guest Count: | B7: ='Client Setup'!B7 | J7: DECOR & PRODUCTION ESTIMATE | M7: DECOR & PRODUCTION ESTIMATE
A8: Location: | B8: ='Client Setup'!B16 | J8: Color | K8: Meaning | M8: ='Client Setup'!B5 | N8: ='Client Setup'!B7&" Guests"
A9: Venue: | E9: Event Time: | F9: ='Client Setup'!B10 | J9: =TEXT('Client Setup'!B6,"MMMM D, YYYY") | K9: Dropdown — click to select | M9: =TEXT('Client Setup'!B6,"MMMM D, YYYY")
A10: Company: | B10: ='Client Setup'!B11 | K10: Manual entry or formula
A11: Program: | B11: ='Client Setup'!B12
A12: Client Hotel: | B12: ='Client Setup'!B13
A13: FLORALS
A14: Item | B14: Vendor | C14: Qty | D14: Unit Price | E14: Our Cost | F14: Client Cost | G14: Tax Rate | H14: Notes / Description | I14: Category | J14: Item | K14: Amount | M14: Category | N14: Amount
A15: TAXABLE FLORAL PRODUCT | J15: =A13 | M15: =A13 | N15: =ROUNDUP(F30/50,0)*50
E16: =C16*D16 | F16: =IFERROR(E16*(1+VLOOKUP(I16,CategoryTable,2,FALSE)),0) | G16: ='Client Setup'!B19 | I16: Décor & Design | J16: =IF(A16="","",A16&" x"&C16) | K16: =IF(A16="","",ROUNDUP(F16/10,0)*10) | M16: Seating | N16: =ROUNDUP(SUM(F35:F42)/50,0)*50
E17: =C17*D17 | F17: =IFERROR(E17*(1+VLOOKUP(I17,CategoryTable,2,FALSE)),0) | G17: ='Client Setup'!B19 | I17: Décor & Design | J17: =IF(A17="","",A17&" x"&C17) | K17: =IF(A17="","",ROUNDUP(F17/10,0)*10) | M17: Lounge Furniture | N17: =ROUNDUP(SUM(F44:F51)/50,0)*50
E18: =C18*D18 | F18: =IFERROR(E18*(1+VLOOKUP(I18,CategoryTable,2,FALSE)),0) | G18: ='Client Setup'!B19 | I18: Décor & Design | J18: =IF(A18="","",A18&" x"&C18) | K18: =IF(A18="","",ROUNDUP(F18/10,0)*10) | M18: Tables | N18: =ROUNDUP(SUM(F53:F60)/50,0)*50
E19: =C19*D19 | F19: =IFERROR(E19*(1+VLOOKUP(I19,CategoryTable,2,FALSE)),0) | G19: ='Client Setup'!B19 | I19: Décor & Design | J19: =IF(A19="","",A19&" x"&C19) | K19: =IF(A19="","",ROUNDUP(F19/10,0)*10) | M19: Decor & Accessories | N19: =ROUNDUP(SUM(F62:F67)/50,0)*50
E20: =C20*D20 | F20: =IFERROR(E20*(1+VLOOKUP(I20,CategoryTable,2,FALSE)),0) | G20: ='Client Setup'!B19 | I20: Décor & Design | J20: =IF(A20="","",A20&" x"&C20) | K20: =IF(A20="","",ROUNDUP(F20/10,0)*10) | M20: Delivery & Fees | N20: =ROUNDUP((SUM(F27:F29)+SUM(F69:F74)+SUM(F91:F95))/50,0)*50
E21: =C21*D21 | F21: =IFERROR(E21*(1+VLOOKUP(I21,CategoryTable,2,FALSE)),0) | G21: ='Client Setup'!B19 | I21: Décor & Design | J21: =IF(A21="","",A21&" x"&C21) | K21: =IF(A21="","",ROUNDUP(F21/10,0)*10) | M21: =A77 | N21: =ROUNDUP(SUM(F80:F89)/50,0)*50
E22: =C22*D22 | F22: =IFERROR(E22*(1+VLOOKUP(I22,CategoryTable,2,FALSE)),0) | G22: ='Client Setup'!B19 | I22: Décor & Design | J22: =IF(A22="","",A22&" x"&C22) | K22: =IF(A22="","",ROUNDUP(F22/10,0)*10) | M22: Tax | N22: =ROUNDUP(F100/50,0)*50
E23: =C23*D23 | F23: =IFERROR(E23*(1+VLOOKUP(I23,CategoryTable,2,FALSE)),0) | G23: ='Client Setup'!B19 | I23: Décor & Design | J23: =IF(A23="","",A23&" x"&C23) | K23: =IF(A23="","",ROUNDUP(F23/10,0)*10)
E24: =C24*D24 | F24: =IFERROR(E24*(1+VLOOKUP(I24,CategoryTable,2,FALSE)),0) | G24: ='Client Setup'!B19 | I24: Décor & Design | J24: =IF(A24="","",A24&" x"&C24) | K24: =IF(A24="","",ROUNDUP(F24/10,0)*10) | M24: TOTAL ESTIMATE | N24: =SUM(N15:N22)
E25: =C25*D25 | F25: =IFERROR(E25*(1+VLOOKUP(I25,CategoryTable,2,FALSE)),0) | G25: ='Client Setup'!B19 | I25: Décor & Design | J25: =IF(A25="","",A25&" x"&C25) | K25: =IF(A25="","",ROUNDUP(F25/10,0)*10) | M25: Guest Count | N25: ='Client Setup'!B7
A26: NON-TAXABLE FLORAL FEES | J26: =IF(A27="","",A27) | K26: =IF(A27="","",ROUNDUP(F27/10,0)*10)
E27: =D27 | F27: =IFERROR(E27*(1+VLOOKUP(I27,CategoryTable,2,FALSE)),0) | G27: 0 | I27: Delivery & Logistics | J27: =IF(A28="","",A28) | K27: =IF(A28="","",ROUNDUP(F28/10,0)*10)
E28: =D28 | F28: =IFERROR(E28*(1+VLOOKUP(I28,CategoryTable,2,FALSE)),0) | G28: 0 | I28: Delivery & Logistics | J28: =IF(A29="","",A29) | K28: =IF(A29="","",ROUNDUP(F29/10,0)*10) | M28: TEAM NOTES
E29: =D29 | F29: =IFERROR(E29*(1+VLOOKUP(I29,CategoryTable,2,FALSE)),0) | G29: 0 | I29: Delivery & Logistics | J29: Floral Subtotal | K29: =SUM(K16:K28) | M29: Floral Vendor:
A30: FLORAL SUBTOTAL | E30: =SUM(E16:E25)+SUM(E27:E29) | F30: =SUM(F16:F25)+SUM(F27:F29)
J31: =A32 | M31: Rental Vendor(s):
A32: RENTALS & LOUNGE | J32: =IF(A35="","",A35&" x"&C35) | K32: =IF(A35="","",ROUNDUP(F35/10,0)*10)
A33: Item | B33: Vendor | C33: Qty | D33: Unit Price | E33: Our Cost | F33: Client Cost | G33: Tax Rate | H33: Notes / Description | J33: =IF(A36="","",A36&" x"&C36) | K33: =IF(A36="","",ROUNDUP(F36/10,0)*10) | M33: AV Vendor:
A34: SEATING (chairs, barstools, banquettes) | J34: =IF(A37="","",A37&" x"&C37) | K34: =IF(A37="","",ROUNDUP(F37/10,0)*10)
E35: =C35*D35 | F35: =IFERROR(E35*(1+VLOOKUP(I35,CategoryTable,2,FALSE)),0) | G35: ='Client Setup'!B19 | I35: Décor & Design | J35: =IF(A38="","",A38&" x"&C38) | K35: =IF(A38="","",ROUNDUP(F38/10,0)*10) | M35: Design Concept:
E36: =C36*D36 | F36: =IFERROR(E36*(1+VLOOKUP(I36,CategoryTable,2,FALSE)),0) | G36: ='Client Setup'!B19 | I36: Décor & Design | J36: =IF(A39="","",A39&" x"&C39) | K36: =IF(A39="","",ROUNDUP(F39/10,0)*10)
E37: =C37*D37 | F37: =IFERROR(E37*(1+VLOOKUP(I37,CategoryTable,2,FALSE)),0) | G37: ='Client Setup'!B19 | I37: Décor & Design | J37: =IF(A40="","",A40&" x"&C40) | K37: =IF(A40="","",ROUNDUP(F40/10,0)*10)
E38: =C38*D38 | F38: =IFERROR(E38*(1+VLOOKUP(I38,CategoryTable,2,FALSE)),0) | G38: ='Client Setup'!B19 | I38: Décor & Design | J38: =IF(A41="","",A41&" x"&C41) | K38: =IF(A41="","",ROUNDUP(F41/10,0)*10) | M38: Logistics:
E39: =C39*D39 | F39: =IFERROR(E39*(1+VLOOKUP(I39,CategoryTable,2,FALSE)),0) | G39: ='Client Setup'!B19 | I39: Décor & Design | J39: =IF(A42="","",A42&" x"&C42) | K39: =IF(A42="","",ROUNDUP(F42/10,0)*10)
E40: =C40*D40 | F40: =IFERROR(E40*(1+VLOOKUP(I40,CategoryTable,2,FALSE)),0) | G40: ='Client Setup'!B19 | I40: Décor & Design | J40: =IF(A44="","",A44&" x"&C44) | K40: =IF(A44="","",ROUNDUP(F44/10,0)*10) | M40: Additional Notes:
E41: =C41*D41 | F41: =IFERROR(E41*(1+VLOOKUP(I41,CategoryTable,2,FALSE)),0) | G41: ='Client Setup'!B19 | I41: Décor & Design | J41: =IF(A45="","",A45&" x"&C45) | K41: =IF(A45="","",ROUNDUP(F45/10,0)*10)
E42: =C42*D42 | F42: =IFERROR(E42*(1+VLOOKUP(I42,CategoryTable,2,FALSE)),0) | G42: ='Client Setup'!B19 | I42: Décor & Design | J42: =IF(A46="","",A46&" x"&C46) | K42: =IF(A46="","",ROUNDUP(F46/10,0)*10)
A43: LOUNGE (sofas, sectionals, club chairs) | J43: =IF(A47="","",A47&" x"&C47) | K43: =IF(A47="","",ROUNDUP(F47/10,0)*10)
E44: =C44*D44 | F44: =IFERROR(E44*(1+VLOOKUP(I44,CategoryTable,2,FALSE)),0) | G44: ='Client Setup'!B19 | I44: Décor & Design | J44: =IF(A48="","",A48&" x"&C48) | K44: =IF(A48="","",ROUNDUP(F48/10,0)*10)
E45: =C45*D45 | F45: =IFERROR(E45*(1+VLOOKUP(I45,CategoryTable,2,FALSE)),0) | G45: ='Client Setup'!B19 | I45: Décor & Design | J45: =IF(A49="","",A49&" x"&C49) | K45: =IF(A49="","",ROUNDUP(F49/10,0)*10)
E46: =C46*D46 | F46: =IFERROR(E46*(1+VLOOKUP(I46,CategoryTable,2,FALSE)),0) | G46: ='Client Setup'!B19 | I46: Décor & Design | J46: =IF(A50="","",A50&" x"&C50) | K46: =IF(A50="","",ROUNDUP(F50/10,0)*10)
E47: =C47*D47 | F47: =IFERROR(E47*(1+VLOOKUP(I47,CategoryTable,2,FALSE)),0) | G47: ='Client Setup'!B19 | I47: Décor & Design | J47: =IF(A51="","",A51&" x"&C51) | K47: =IF(A51="","",ROUNDUP(F51/10,0)*10)
E48: =C48*D48 | F48: =IFERROR(E48*(1+VLOOKUP(I48,CategoryTable,2,FALSE)),0) | G48: ='Client Setup'!B19 | I48: Décor & Design | J48: =IF(A53="","",A53&" x"&C53) | K48: =IF(A53="","",ROUNDUP(F53/10,0)*10)
E49: =C49*D49 | F49: =IFERROR(E49*(1+VLOOKUP(I49,CategoryTable,2,FALSE)),0) | G49: ='Client Setup'!B19 | I49: Décor & Design | J49: =IF(A54="","",A54&" x"&C54) | K49: =IF(A54="","",ROUNDUP(F54/10,0)*10)
E50: =C50*D50 | F50: =IFERROR(E50*(1+VLOOKUP(I50,CategoryTable,2,FALSE)),0) | G50: ='Client Setup'!B19 | I50: Décor & Design | J50: =IF(A55="","",A55&" x"&C55) | K50: =IF(A55="","",ROUNDUP(F55/10,0)*10)
E51: =C51*D51 | F51: =IFERROR(E51*(1+VLOOKUP(I51,CategoryTable,2,FALSE)),0) | G51: ='Client Setup'!B19 | I51: Décor & Design | J51: =IF(A56="","",A56&" x"&C56) | K51: =IF(A56="","",ROUNDUP(F56/10,0)*10)
A52: TABLES (cocktail, coffee, side, dining) | J52: =IF(A57="","",A57&" x"&C57) | K52: =IF(A57="","",ROUNDUP(F57/10,0)*10)
E53: =C53*D53 | F53: =IFERROR(E53*(1+VLOOKUP(I53,CategoryTable,2,FALSE)),0) | G53: ='Client Setup'!B19 | I53: Décor & Design | J53: =IF(A58="","",A58&" x"&C58) | K53: =IF(A58="","",ROUNDUP(F58/10,0)*10)
E54: =C54*D54 | F54: =IFERROR(E54*(1+VLOOKUP(I54,CategoryTable,2,FALSE)),0) | G54: ='Client Setup'!B19 | I54: Décor & Design | J54: =IF(A59="","",A59&" x"&C59) | K54: =IF(A59="","",ROUNDUP(F59/10,0)*10)
E55: =C55*D55 | F55: =IFERROR(E55*(1+VLOOKUP(I55,CategoryTable,2,FALSE)),0) | G55: ='Client Setup'!B19 | I55: Décor & Design | J55: =IF(A60="","",A60&" x"&C60) | K55: =IF(A60="","",ROUNDUP(F60/10,0)*10)
E56: =C56*D56 | F56: =IFERROR(E56*(1+VLOOKUP(I56,CategoryTable,2,FALSE)),0) | G56: ='Client Setup'!B19 | I56: Décor & Design | J56: =IF(A62="","",A62&" x"&C62) | K56: =IF(A62="","",ROUNDUP(F62/10,0)*10)
E57: =C57*D57 | F57: =IFERROR(E57*(1+VLOOKUP(I57,CategoryTable,2,FALSE)),0) | G57: ='Client Setup'!B19 | I57: Décor & Design | J57: =IF(A63="","",A63&" x"&C63) | K57: =IF(A63="","",ROUNDUP(F63/10,0)*10)
E58: =C58*D58 | F58: =IFERROR(E58*(1+VLOOKUP(I58,CategoryTable,2,FALSE)),0) | G58: ='Client Setup'!B19 | I58: Décor & Design | J58: =IF(A64="","",A64&" x"&C64) | K58: =IF(A64="","",ROUNDUP(F64/10,0)*10)
E59: =C59*D59 | F59: =IFERROR(E59*(1+VLOOKUP(I59,CategoryTable,2,FALSE)),0) | G59: ='Client Setup'!B19 | I59: Décor & Design | J59: =IF(A65="","",A65&" x"&C65) | K59: =IF(A65="","",ROUNDUP(F65/10,0)*10)
E60: =C60*D60 | F60: =IFERROR(E60*(1+VLOOKUP(I60,CategoryTable,2,FALSE)),0) | G60: ='Client Setup'!B19 | I60: Décor & Design | J60: =IF(A66="","",A66&" x"&C66) | K60: =IF(A66="","",ROUNDUP(F66/10,0)*10)
A61: RUGS, DECOR & ACCESSORIES | J61: =IF(A67="","",A67&" x"&C67) | K61: =IF(A67="","",ROUNDUP(F67/10,0)*10)
E62: =C62*D62 | F62: =IFERROR(E62*(1+VLOOKUP(I62,CategoryTable,2,FALSE)),0) | G62: ='Client Setup'!B19 | I62: Décor & Design | J62: =IF(A69="","",A69) | K62: =IF(A69="","",ROUNDUP(F69/10,0)*10)
E63: =C63*D63 | F63: =IFERROR(E63*(1+VLOOKUP(I63,CategoryTable,2,FALSE)),0) | G63: ='Client Setup'!B19 | I63: Décor & Design | J63: =IF(A70="","",A70) | K63: =IF(A70="","",ROUNDUP(F70/10,0)*10)
E64: =C64*D64 | F64: =IFERROR(E64*(1+VLOOKUP(I64,CategoryTable,2,FALSE)),0) | G64: ='Client Setup'!B19 | I64: Décor & Design | J64: =IF(A71="","",A71) | K64: =IF(A71="","",ROUNDUP(F71/10,0)*10)
E65: =C65*D65 | F65: =IFERROR(E65*(1+VLOOKUP(I65,CategoryTable,2,FALSE)),0) | G65: ='Client Setup'!B19 | I65: Décor & Design | J65: =IF(A72="","",A72) | K65: =IF(A72="","",ROUNDUP(F72/10,0)*10)
E66: =C66*D66 | F66: =IFERROR(E66*(1+VLOOKUP(I66,CategoryTable,2,FALSE)),0) | G66: ='Client Setup'!B19 | I66: Décor & Design | J66: =IF(A73="","",A73) | K66: =IF(A73="","",ROUNDUP(F73/10,0)*10)
E67: =C67*D67 | F67: =IFERROR(E67*(1+VLOOKUP(I67,CategoryTable,2,FALSE)),0) | G67: ='Client Setup'!B19 | I67: Décor & Design | J67: =IF(A74="","",A74) | K67: =IF(A74="","",ROUNDUP(F74/10,0)*10)
A68: NON-TAXABLE RENTAL FEES | J68: Rentals & Lounge Subtotal | K68: =SUM(K32:K67)
E69: =D69 | F69: =IFERROR(E69*(1+VLOOKUP(I69,CategoryTable,2,FALSE)),0) | G69: 0 | I69: Delivery & Logistics
E70: =D70 | F70: =IFERROR(E70*(1+VLOOKUP(I70,CategoryTable,2,FALSE)),0) | G70: 0 | I70: Delivery & Logistics | J70: =A77
E71: =D71 | F71: =IFERROR(E71*(1+VLOOKUP(I71,CategoryTable,2,FALSE)),0) | G71: 0 | I71: Delivery & Logistics | J71: =IF(A80="","",A80&" x"&C80) | K71: =IF(A80="","",ROUNDUP(F80/10,0)*10)
E72: =D72 | F72: =IFERROR(E72*(1+VLOOKUP(I72,CategoryTable,2,FALSE)),0) | G72: 0 | I72: Delivery & Logistics | J72: =IF(A81="","",A81&" x"&C81) | K72: =IF(A81="","",ROUNDUP(F81/10,0)*10)
E73: =D73 | F73: =IFERROR(E73*(1+VLOOKUP(I73,CategoryTable,2,FALSE)),0) | G73: 0 | I73: Delivery & Logistics | J73: =IF(A82="","",A82&" x"&C82) | K73: =IF(A82="","",ROUNDUP(F82/10,0)*10)
E74: =D74 | F74: =IFERROR(E74*(1+VLOOKUP(I74,CategoryTable,2,FALSE)),0) | G74: 0 | I74: Delivery & Logistics | J74: =IF(A83="","",A83&" x"&C83) | K74: =IF(A83="","",ROUNDUP(F83/10,0)*10)
A75: RENTALS & LOUNGE SUBTOTAL | E75: =SUM(E35:E42)+SUM(E44:E51)+SUM(E53:E60)+SUM(E62:E67)+SUM(E69:E74) | F75: =SUM(F35:F42)+SUM(F44:F51)+SUM(F53:F60)+SUM(F62:F67)+SUM(F69:F74) | J75: =IF(A84="","",A84&" x"&C84) | K75: =IF(A84="","",ROUNDUP(F84/10,0)*10)
J76: =IF(A85="","",A85&" x"&C85) | K76: =IF(A85="","",ROUNDUP(F85/10,0)*10)
A77: AV / PRODUCTION | J77: =IF(A86="","",A86&" x"&C86) | K77: =IF(A86="","",ROUNDUP(F86/10,0)*10)
A78: Item | B78: Vendor | C78: Qty | D78: Unit Price | E78: Our Cost | F78: Client Cost | G78: Tax Rate | H78: Notes / Description | J78: =IF(A87="","",A87&" x"&C87) | K78: =IF(A87="","",ROUNDUP(F87/10,0)*10)
A79: TAXABLE AV & PRODUCTION EQUIPMENT | J79: =IF(A88="","",A88&" x"&C88) | K79: =IF(A88="","",ROUNDUP(F88/10,0)*10)
E80: =C80*D80 | F80: =IFERROR(E80*(1+VLOOKUP(I80,CategoryTable,2,FALSE)),0) | G80: ='Client Setup'!B19 | I80: AV & Production | J80: =IF(A89="","",A89&" x"&C89) | K80: =IF(A89="","",ROUNDUP(F89/10,0)*10)
E81: =C81*D81 | F81: =IFERROR(E81*(1+VLOOKUP(I81,CategoryTable,2,FALSE)),0) | G81: ='Client Setup'!B19 | I81: AV & Production | J81: =IF(A91="","",A91) | K81: =IF(A91="","",ROUNDUP(F91/10,0)*10)
E82: =C82*D82 | F82: =IFERROR(E82*(1+VLOOKUP(I82,CategoryTable,2,FALSE)),0) | G82: ='Client Setup'!B19 | I82: AV & Production | J82: =IF(A92="","",A92) | K82: =IF(A92="","",ROUNDUP(F92/10,0)*10)
E83: =C83*D83 | F83: =IFERROR(E83*(1+VLOOKUP(I83,CategoryTable,2,FALSE)),0) | G83: ='Client Setup'!B19 | I83: AV & Production | J83: =IF(A93="","",A93) | K83: =IF(A93="","",ROUNDUP(F93/10,0)*10)
E84: =C84*D84 | F84: =IFERROR(E84*(1+VLOOKUP(I84,CategoryTable,2,FALSE)),0) | G84: ='Client Setup'!B19 | I84: AV & Production | J84: =IF(A94="","",A94) | K84: =IF(A94="","",ROUNDUP(F94/10,0)*10)
E85: =C85*D85 | F85: =IFERROR(E85*(1+VLOOKUP(I85,CategoryTable,2,FALSE)),0) | G85: ='Client Setup'!B19 | I85: AV & Production | J85: =IF(A95="","",A95) | K85: =IF(A95="","",ROUNDUP(F95/10,0)*10)
E86: =C86*D86 | F86: =IFERROR(E86*(1+VLOOKUP(I86,CategoryTable,2,FALSE)),0) | G86: ='Client Setup'!B19 | I86: AV & Production | J86: AV / Production Subtotal | K86: =SUM(K71:K85)
E87: =C87*D87 | F87: =IFERROR(E87*(1+VLOOKUP(I87,CategoryTable,2,FALSE)),0) | G87: ='Client Setup'!B19 | I87: AV & Production
E88: =C88*D88 | F88: =IFERROR(E88*(1+VLOOKUP(I88,CategoryTable,2,FALSE)),0) | G88: ='Client Setup'!B19 | I88: AV & Production | J88: Tax | K88: =ROUNDUP(F100/10,0)*10
E89: =C89*D89 | F89: =IFERROR(E89*(1+VLOOKUP(I89,CategoryTable,2,FALSE)),0) | G89: ='Client Setup'!B19 | I89: AV & Production
A90: NON-TAXABLE AV FEES & LABOR | J90: TOTAL | K90: =K29+K68+K86+K88
A91: AV Tech Labor | E91: =D91 | F91: =IFERROR(E91*(1+VLOOKUP(I91,CategoryTable,2,FALSE)),0) | G91: 0 | I91: Staffing & Labor
A92: Delivery / Setup | E92: =D92 | F92: =IFERROR(E92*(1+VLOOKUP(I92,CategoryTable,2,FALSE)),0) | G92: 0 | I92: Staffing & Labor
A93: Strike / Removal | E93: =D93 | F93: =IFERROR(E93*(1+VLOOKUP(I93,CategoryTable,2,FALSE)),0) | G93: 0 | I93: Staffing & Labor
E94: =D94 | F94: =IFERROR(E94*(1+VLOOKUP(I94,CategoryTable,2,FALSE)),0) | G94: 0 | I94: Staffing & Labor
E95: =D95 | F95: =IFERROR(E95*(1+VLOOKUP(I95,CategoryTable,2,FALSE)),0) | G95: 0 | I95: Staffing & Labor
A96: AV / PRODUCTION SUBTOTAL | E96: =SUM(E80:E89)+SUM(E91:E95) | F96: =SUM(F80:F89)+SUM(F91:F95)
A98: ESTIMATE SUMMARY
A99: Taxable Product Subtotal | E99: =SUM(E16:E25)+SUM(E35:E42)+SUM(E44:E51)+SUM(E53:E60)+SUM(E62:E67)+SUM(E80:E89) | F99: =SUM(F16:F25)+SUM(F35:F42)+SUM(F44:F51)+SUM(F53:F60)+SUM(F62:F67)+SUM(F80:F89)
A100: Sales Tax | E100: =IFERROR(E99*'Client Setup'!B19,0) | F100: =IFERROR(F99*'Client Setup'!B19,0)
A101: Non-Taxable Fees Subtotal | E101: =SUM(E27:E29)+SUM(E69:E74)+SUM(E91:E95) | F101: =SUM(F27:F29)+SUM(F69:F74)+SUM(F91:F95)
A102: CC Processing Fee | E102: =F102 | F102: =IFERROR((F99+F100+F101)*'Client Setup'!C35,0)
A103: Third-Party Commission | E103: =F103 | F103: =IFERROR((F99+F100+F101)*'Client Setup'!C36,0)
...

Sheet SAMPLE Decor Estimate
A2: Decor & Production Estimate
A4: EVENT INFO (from Client Setup) | J4: DETAILED CLIENT VIEW | M4: SUMMARY VIEW
A5: Client: | B5: ='Client Setup'!B5 | J5: Itemized — each section is one Canva slide | M5: Category totals for client
A6: Event Date: | B6: ='Client Setup'!B6
A7: Guest Count: | B7: ='Client Setup'!B7 | J7: DECOR & PRODUCTION ESTIMATE | M7: DECOR & PRODUCTION ESTIMATE
A8: Location: | B8: ='Client Setup'!B16 | J8: Color | K8: Meaning | M8: ='Client Setup'!B5 | N8: ='Client Setup'!B7&" Guests"
A9: Venue: | B9: 101 Constitution Ave NW, Washington DC | E9: Event Time: | F9: ='Client Setup'!B10 | J9: =TEXT('Client Setup'!B6,"MMMM D, YYYY") | K9: Dropdown — click to select | M9: =TEXT('Client Setup'!B6,"MMMM D, YYYY")
A10: Company: | B10: ='Client Setup'!B11 | K10: Manual entry or formula
A11: Program: | B11: ='Client Setup'!B12
A12: Client Hotel: | B12: ='Client Setup'!B13
A13: FLORALS
A14: Item | B14: Vendor | C14: Qty | D14: Unit Price | E14: Our Cost | F14: Client Cost | G14: Tax Rate | H14: Notes / Description | I14: Category | J14: Item | K14: Amount | M14: Category | N14: Amount
A15: TAXABLE FLORAL PRODUCT | J15: =A13 | M15: =A13 | N15: =ROUNDUP(F30/50,0)*50
A16: 4ft Table Florals | B16: Flowers at 38 | C16: 14 | D16: 90 | E16: =C16*D16 | F16: =IFERROR(E16*(1+VLOOKUP(I16,CategoryTable,2,FALSE)),0) | G16: ='Client Setup'!B19 | H16: Trio gold bud vases, cherry blossom, ranunculus, astilbe + 2 votives | I16: Décor & Design | J16: =IF(A16="","",A16&" x"&C16) | K16: =IF(A16="","",ROUNDUP(F16/10,0)*10) | M16: Seating | N16: =ROUNDUP(SUM(F35:F42)/50,0)*50
A17: Cocktail Table Florals | B17: Flowers at 38 | C17: 14 | D17: 31 | E17: =C17*D17 | F17: =IFERROR(E17*(1+VLOOKUP(I17,CategoryTable,2,FALSE)),0) | G17: ='Client Setup'!B19 | H17: Single bud vase + single ribbed votive | I17: Décor & Design | J17: =IF(A17="","",A17&" x"&C17) | K17: =IF(A17="","",ROUNDUP(F17/10,0)*10) | M17: Lounge Furniture | N17: =ROUNDUP(SUM(F44:F51)/50,0)*50
A18: Side Table Florals | B18: Flowers at 38 | C18: 2 | D18: 96 | E18: =C18*D18 | F18: =IFERROR(E18*(1+VLOOKUP(I18,CategoryTable,2,FALSE)),0) | G18: ='Client Setup'!B19 | H18: Trio gold bud vases, cherry blossom, ranunculus, astilbe + 4 votives | I18: Décor & Design | J18: =IF(A18="","",A18&" x"&C18) | K18: =IF(A18="","",ROUNDUP(F18/10,0)*10) | M18: Tables | N18: =ROUNDUP(SUM(F53:F60)/50,0)*50
E19: =C19*D19 | F19: =IFERROR(E19*(1+VLOOKUP(I19,CategoryTable,2,FALSE)),0) | G19: ='Client Setup'!B19 | I19: Décor & Design | J19: =IF(A19="","",A19&" x"&C19) | K19: =IF(A19="","",ROUNDUP(F19/10,0)*10) | M19: Decor & Accessories | N19: =ROUNDUP(SUM(F62:F67)/50,0)*50
E20: =C20*D20 | F20: =IFERROR(E20*(1+VLOOKUP(I20,CategoryTable,2,FALSE)),0) | G20: ='Client Setup'!B19 | I20: Décor & Design | J20: =IF(A20="","",A20&" x"&C20) | K20: =IF(A20="","",ROUNDUP(F20/10,0)*10) | M20: Delivery & Fees | N20: =ROUNDUP((SUM(F27:F29)+SUM(F69:F74)+SUM(F91:F95))/50,0)*50
E21: =C21*D21 | F21: =IFERROR(E21*(1+VLOOKUP(I21,CategoryTable,2,FALSE)),0) | G21: ='Client Setup'!B19 | I21: Décor & Design | J21: =IF(A21="","",A21&" x"&C21) | K21: =IF(A21="","",ROUNDUP(F21/10,0)*10) | M21: =A77 | N21: =ROUNDUP(SUM(F80:F89)/50,0)*50
E22: =C22*D22 | F22: =IFERROR(E22*(1+VLOOKUP(I22,CategoryTable,2,FALSE)),0) | G22: ='Client Setup'!B19 | I22: Décor & Design | J22: =IF(A22="","",A22&" x"&C22) | K22: =IF(A22="","",ROUNDUP(F22/10,0)*10) | M22: Tax | N22: =ROUNDUP(F100/50,0)*50
E23: =C23*D23 | F23: =IFERROR(E23*(1+VLOOKUP(I23,CategoryTable,2,FALSE)),0) | G23: ='Client Setup'!B19 | I23: Décor & Design | J23: =IF(A23="","",A23&" x"&C23) | K23: =IF(A23="","",ROUNDUP(F23/10,0)*10)
E24: =C24*D24 | F24: =IFERROR(E24*(1+VLOOKUP(I24,CategoryTable,2,FALSE)),0) | G24: ='Client Setup'!B19 | I24: Décor & Design | J24: =IF(A24="","",A24&" x"&C24) | K24: =IF(A24="","",ROUNDUP(F24/10,0)*10) | M24: TOTAL ESTIMATE | N24: =SUM(N15:N22)
E25: =C25*D25 | F25: =IFERROR(E25*(1+VLOOKUP(I25,CategoryTable,2,FALSE)),0) | G25: ='Client Setup'!B19 | I25: Décor & Design | J25: =IF(A25="","",A25&" x"&C25) | K25: =IF(A25="","",ROUNDUP(F25/10,0)*10) | M25: Guest Count | N25: ='Client Setup'!B7
A26: NON-TAXABLE FLORAL FEES | J26: =IF(A27="","",A27) | K26: =IF(A27="","",ROUNDUP(F27/10,0)*10)
A27: Delivery/Setup & Strike | B27: Flowers at 38 | D27: 188.6 | E27: =D27 | F27: =IFERROR(E27*(1+VLOOKUP(I27,CategoryTable,2,FALSE)),0) | G27: 0 | H27: Tax exempt on vendor invoice — resale on file | I27: Delivery & Logistics | J27: =IF(A28="","",A28) | K27: =IF(A28="","",ROUNDUP(F28/10,0)*10)
E28: =D28 | F28: =IFERROR(E28*(1+VLOOKUP(I28,CategoryTable,2,FALSE)),0) | G28: 0 | I28: Delivery & Logistics | J28: =IF(A29="","",A29) | K28: =IF(A29="","",ROUNDUP(F29/10,0)*10) | M28: TEAM NOTES
E29: =D29 | F29: =IFERROR(E29*(1+VLOOKUP(I29,CategoryTable,2,FALSE)),0) | G29: 0 | I29: Delivery & Logistics | J29: Floral Subtotal | K29: =SUM(K16:K28) | M29: Floral Vendor:
A30: FLORAL SUBTOTAL | E30: =SUM(E16:E25)+SUM(E27:E29) | F30: =SUM(F16:F25)+SUM(F27:F29)
J31: =A32 | M31: Rental Vendor(s):
A32: RENTALS & LOUNGE | J32: =IF(A35="","",A35&" x"&C35) | K32: =IF(A35="","",ROUNDUP(F35/10,0)*10)
A33: Item | B33: Vendor | C33: Qty | D33: Unit Price | E33: Our Cost | F33: Client Cost | G33: Tax Rate | H33: Notes / Description | J33: =IF(A36="","",A36&" x"&C36) | K33: =IF(A36="","",ROUNDUP(F36/10,0)*10) | M33: AV Vendor:
A34: SEATING (chairs, barstools, banquettes) | J34: =IF(A37="","",A37&" x"&C37) | K34: =IF(A37="","",ROUNDUP(F37/10,0)*10)
A35: Paris Oval Back Chair | B35: White Glove | C35: 84 | D35: 21 | E35: =C35*D35 | F35: =IFERROR(E35*(1+VLOOKUP(I35,CategoryTable,2,FALSE)),0) | G35: ='Client Setup'!B19 | I35: Décor & Design | J35: =IF(A38="","",A38&" x"&C38) | K35: =IF(A38="","",ROUNDUP(F38/10,0)*10) | M35: Design Concept:
A36: Ritz Mauve Circular Banquette | B36: White Glove | C36: 2 | D36: 395 | E36: =C36*D36 | F36: =IFERROR(E36*(1+VLOOKUP(I36,CategoryTable,2,FALSE)),0) | G36: ='Client Setup'!B19 | I36: Décor & Design | J36: =IF(A39="","",A39&" x"&C39) | K36: =IF(A39="","",ROUNDUP(F39/10,0)*10)
E37: =C37*D37 | F37: =IFERROR(E37*(1+VLOOKUP(I37,CategoryTable,2,FALSE)),0) | G37: ='Client Setup'!B19 | I37: Décor & Design | J37: =IF(A40="","",A40&" x"&C40) | K37: =IF(A40="","",ROUNDUP(F40/10,0)*10)
E38: =C38*D38 | F38: =IFERROR(E38*(1+VLOOKUP(I38,CategoryTable,2,FALSE)),0) | G38: ='Client Setup'!B19 | I38: Décor & Design | J38: =IF(A41="","",A41&" x"&C41) | K38: =IF(A41="","",ROUNDUP(F41/10,0)*10) | M38: Logistics:
E39: =C39*D39 | F39: =IFERROR(E39*(1+VLOOKUP(I39,CategoryTable,2,FALSE)),0) | G39: ='Client Setup'!B19 | I39: Décor & Design | J39: =IF(A42="","",A42&" x"&C42) | K39: =IF(A42="","",ROUNDUP(F42/10,0)*10)
E40: =C40*D40 | F40: =IFERROR(E40*(1+VLOOKUP(I40,CategoryTable,2,FALSE)),0) | G40: ='Client Setup'!B19 | I40: Décor & Design | J40: =IF(A44="","",A44&" x"&C44) | K40: =IF(A44="","",ROUNDUP(F44/10,0)*10) | M40: Additional Notes:
E41: =C41*D41 | F41: =IFERROR(E41*(1+VLOOKUP(I41,CategoryTable,2,FALSE)),0) | G41: ='Client Setup'!B19 | I41: Décor & Design | J41: =IF(A45="","",A45&" x"&C45) | K41: =IF(A45="","",ROUNDUP(F45/10,0)*10)
E42: =C42*D42 | F42: =IFERROR(E42*(1+VLOOKUP(I42,CategoryTable,2,FALSE)),0) | G42: ='Client Setup'!B19 | I42: Décor & Design | J42: =IF(A46="","",A46&" x"&C46) | K42: =IF(A46="","",ROUNDUP(F46/10,0)*10)
A43: LOUNGE (sofas, sectionals, club chairs) | J43: =IF(A47="","",A47&" x"&C47) | K43: =IF(A47="","",ROUNDUP(F47/10,0)*10)
A44: Gillian Club Chair | B44: White Glove | C44: 4 | D44: 165 | E44: =C44*D44 | F44: =IFERROR(E44*(1+VLOOKUP(I44,CategoryTable,2,FALSE)),0) | G44: ='Client Setup'!B19 | I44: Décor & Design | J44: =IF(A48="","",A48&" x"&C48) | K44: =IF(A48="","",ROUNDUP(F48/10,0)*10)
A45: Drift LEFT ARM Section | B45: White Glove | C45: 2 | D45: 237.5 | E45: =C45*D45 | F45: =IFERROR(E45*(1+VLOOKUP(I45,CategoryTable,2,FALSE)),0) | G45: ='Client Setup'!B19 | H45: Creating (2) 3-piece sectionals | I45: Décor & Design | J45: =IF(A49="","",A49&" x"&C49) | K45: =IF(A49="","",ROUNDUP(F49/10,0)*10)
A46: Drift CENTER Section | B46: White Glove | C46: 2 | D46: 237.5 | E46: =C46*D46 | F46: =IFERROR(E46*(1+VLOOKUP(I46,CategoryTable,2,FALSE)),0) | G46: ='Client Setup'!B19 | H46: Creating (2) 3-piece sectionals | I46: Décor & Design | J46: =IF(A50="","",A50&" x"&C50) | K46: =IF(A50="","",ROUNDUP(F50/10,0)*10)
A47: Drift RIGHT ARM Section | B47: White Glove | C47: 2 | D47: 237.5 | E47: =C47*D47 | F47: =IFERROR(E47*(1+VLOOKUP(I47,CategoryTable,2,FALSE)),0) | G47: ='Client Setup'!B19 | H47: Creating (2) 3-piece sectionals | I47: Décor & Design | J47: =IF(A51="","",A51&" x"&C51) | K47: =IF(A51="","",ROUNDUP(F51/10,0)*10)
E48: =C48*D48 | F48: =IFERROR(E48*(1+VLOOKUP(I48,CategoryTable,2,FALSE)),0) | G48: ='Client Setup'!B19 | I48: Décor & Design | J48: =IF(A53="","",A53&" x"&C53) | K48: =IF(A53="","",ROUNDUP(F53/10,0)*10)
E49: =C49*D49 | F49: =IFERROR(E49*(1+VLOOKUP(I49,CategoryTable,2,FALSE)),0) | G49: ='Client Setup'!B19 | I49: Décor & Design | J49: =IF(A54="","",A54&" x"&C54) | K49: =IF(A54="","",ROUNDUP(F54/10,0)*10)
E50: =C50*D50 | F50: =IFERROR(E50*(1+VLOOKUP(I50,CategoryTable,2,FALSE)),0) | G50: ='Client Setup'!B19 | I50: Décor & Design | J50: =IF(A55="","",A55&" x"&C55) | K50: =IF(A55="","",ROUNDUP(F55/10,0)*10)
E51: =C51*D51 | F51: =IFERROR(E51*(1+VLOOKUP(I51,CategoryTable,2,FALSE)),0) | G51: ='Client Setup'!B19 | I51: Décor & Design | J51: =IF(A56="","",A56&" x"&C56) | K51: =IF(A56="","",ROUNDUP(F56/10,0)*10)
A52: TABLES (cocktail, coffee, side, dining) | J52: =IF(A57="","",A57&" x"&C57) | K52: =IF(A57="","",ROUNDUP(F57/10,0)*10)
A53: Branch & Root Side Table | B53: White Glove | C53: 4 | D53: 69 | E53: =C53*D53 | F53: =IFERROR(E53*(1+VLOOKUP(I53,CategoryTable,2,FALSE)),0) | G53: ='Client Setup'!B19 | I53: Décor & Design | J53: =IF(A58="","",A58&" x"&C58) | K53: =IF(A58="","",ROUNDUP(F58/10,0)*10)
A54: Belmont Coffee Table | B54: White Glove | C54: 2 | D54: 129 | E54: =C54*D54 | F54: =IFERROR(E54*(1+VLOOKUP(I54,CategoryTable,2,FALSE)),0) | G54: ='Client Setup'!B19 | I54: Décor & Design | J54: =IF(A59="","",A59&" x"&C59) | K54: =IF(A59="","",ROUNDUP(F59/10,0)*10)
A55: Talia Cocktail Table | B55: White Glove | C55: 14 | D55: 129 | E55: =C55*D55 | F55: =IFERROR(E55*(1+VLOOKUP(I55,CategoryTable,2,FALSE)),0) | G55: ='Client Setup'!B19 | I55: Décor & Design | J55: =IF(A60="","",A60&" x"&C60) | K55: =IF(A60="","",ROUNDUP(F60/10,0)*10)
E56: =C56*D56 | F56: =IFERROR(E56*(1+VLOOKUP(I56,CategoryTable,2,FALSE)),0) | G56: ='Client Setup'!B19 | I56: Décor & Design | J56: =IF(A62="","",A62&" x"&C62) | K56: =IF(A62="","",ROUNDUP(F62/10,0)*10)
E57: =C57*D57 | F57: =IFERROR(E57*(1+VLOOKUP(I57,CategoryTable,2,FALSE)),0) | G57: ='Client Setup'!B19 | I57: Décor & Design | J57: =IF(A63="","",A63&" x"&C63) | K57: =IF(A63="","",ROUNDUP(F63/10,0)*10)
E58: =C58*D58 | F58: =IFERROR(E58*(1+VLOOKUP(I58,CategoryTable,2,FALSE)),0) | G58: ='Client Setup'!B19 | I58: Décor & Design | J58: =IF(A64="","",A64&" x"&C64) | K58: =IF(A64="","",ROUNDUP(F64/10,0)*10)
E59: =C59*D59 | F59: =IFERROR(E59*(1+VLOOKUP(I59,CategoryTable,2,FALSE)),0) | G59: ='Client Setup'!B19 | I59: Décor & Design | J59: =IF(A65="","",A65&" x"&C65) | K59: =IF(A65="","",ROUNDUP(F65/10,0)*10)
E60: =C60*D60 | F60: =IFERROR(E60*(1+VLOOKUP(I60,CategoryTable,2,FALSE)),0) | G60: ='Client Setup'!B19 | I60: Décor & Design | J60: =IF(A66="","",A66&" x"&C66) | K60: =IF(A66="","",ROUNDUP(F66/10,0)*10)
A61: RUGS, DECOR & ACCESSORIES | J61: =IF(A67="","",A67&" x"&C67) | K61: =IF(A67="","",ROUNDUP(F67/10,0)*10)
A62: Edith Pink Medallion Rug (5x8) | B62: White Glove | C62: 2 | D62: 69 | E62: =C62*D62 | F62: =IFERROR(E62*(1+VLOOKUP(I62,CategoryTable,2,FALSE)),0) | G62: ='Client Setup'!B19 | I62: Décor & Design | J62: =IF(A69="","",A69) | K62: =IF(A69="","",ROUNDUP(F69/10,0)*10)
A63: 11ft Grand Arch Cherry Blossom Tree | B63: Dalissa Events | C63: 2 | D63: 450 | E63: =C63*D63 | F63: =IFERROR(E63*(1+VLOOKUP(I63,CategoryTable,2,FALSE)),0) | G63: ='Client Setup'!B19 | H63: Blush/Light Pink, 11ft H x 8ft W | I63: Décor & Design | J63: =IF(A70="","",A70) | K63: =IF(A70="","",ROUNDUP(F70/10,0)*10)
A64: Canopy Weight (2lb) | B64: Dalissa Events | C64: 12 | D64: 0 | E64: =C64*D64 | F64: =IFERROR(E64*(1+VLOOKUP(I64,CategoryTable,2,FALSE)),0) | G64: ='Client Setup'!B19 | H64: Included with trees | I64: Décor & Design | J64: =IF(A71="","",A71) | K64: =IF(A71="","",ROUNDUP(F71/10,0)*10)
E65: =C65*D65 | F65: =IFERROR(E65*(1+VLOOKUP(I65,CategoryTable,2,FALSE)),0) | G65: ='Client Setup'!B19 | I65: Décor & Design | J65: =IF(A72="","",A72) | K65: =IF(A72="","",ROUNDUP(F72/10,0)*10)
E66: =C66*D66 | F66: =IFERROR(E66*(1+VLOOKUP(I66,CategoryTable,2,FALSE)),0) | G66: ='Client Setup'!B19 | I66: Décor & Design | J66: =IF(A73="","",A73) | K66: =IF(A73="","",ROUNDUP(F73/10,0)*10)
E67: =C67*D67 | F67: =IFERROR(E67*(1+VLOOKUP(I67,CategoryTable,2,FALSE)),0) | G67: ='Client Setup'!B19 | I67: Décor & Design | J67: =IF(A74="","",A74) | K67: =IF(A74="","",ROUNDUP(F74/10,0)*10)
A68: NON-TAXABLE RENTAL FEES | J68: Rentals & Lounge Subtotal | K68: =SUM(K32:K67)
A69: Delivery / Pickup | B69: White Glove | D69: 1636.91 | E69: =D69 | F69: =IFERROR(E69*(1+VLOOKUP(I69,CategoryTable,2,FALSE)),0) | G69: 0 | I69: Delivery & Logistics
A70: Damage Waiver | B70: White Glove | D70: 793.54 | E70: =D70 | F70: =IFERROR(E70*(1+VLOOKUP(I70,CategoryTable,2,FALSE)),0) | G70: 0 | H70: 11% damage waiver — not taxed | I70: Delivery & Logistics | J70: =A77
A71: Chair Pull / Placement | B71: White Glove | D71: 84 | E71: =D71 | F71: =IFERROR(E71*(1+VLOOKUP(I71,CategoryTable,2,FALSE)),0) | G71: 0 | I71: Delivery & Logistics | J71: =IF(A80="","",A80&" x"&C80) | K71: =IF(A80="","",ROUNDUP(F80/10,0)*10)
A72: Chair Placement | B72: White Glove | D72: 84 | E72: =D72 | F72: =IFERROR(E72*(1+VLOOKUP(I72,CategoryTable,2,FALSE)),0) | G72: 0 | I72: Delivery & Logistics | J72: =IF(A81="","",A81&" x"&C81) | K72: =IF(A81="","",ROUNDUP(F81/10,0)*10)
A73: Damage Waiver | B73: Dalissa Events | D73: 91.84 | E73: =D73 | F73: =IFERROR(E73*(1+VLOOKUP(I73,CategoryTable,2,FALSE)),0) | G73: 0 | H73: Unintentional damage waiver | I73: Delivery & Logistics | J73: =IF(A82="","",A82&" x"&C82) | K73: =IF(A82="","",ROUNDUP(F82/10,0)*10)
A74: Delivery & Pickup | B74: Dalissa Events | D74: 248.02 | E74: =D74 | F74: =IFERROR(E74*(1+VLOOKUP(I74,CategoryTable,2,FALSE)),0) | G74: 0 | H74: Drop-off $124.01 + Pickup $124.01 | I74: Delivery & Logistics | J74: =IF(A83="","",A83&" x"&C83) | K74: =IF(A83="","",ROUNDUP(F83/10,0)*10)
A75: RENTALS & LOUNGE SUBTOTAL | E75: =SUM(E35:E42)+SUM(E44:E51)+SUM(E53:E60)+SUM(E62:E67)+SUM(E69:E74) | F75: =SUM(F35:F42)+SUM(F44:F51)+SUM(F53:F60)+SUM(F62:F67)+SUM(F69:F74) | J75: =IF(A84="","",A84&" x"&C84) | K75: =IF(A84="","",ROUNDUP(F84/10,0)*10)
J76: =IF(A85="","",A85&" x"&C85) | K76: =IF(A85="","",ROUNDUP(F85/10,0)*10)
A77: AV / PRODUCTION | J77: =IF(A86="","",A86&" x"&C86) | K77: =IF(A86="","",ROUNDUP(F86/10,0)*10)
A78: Item | B78: Vendor | C78: Qty | D78: Unit Price | E78: Our Cost | F78: Client Cost | G78: Tax Rate | H78: Notes / Description | J78: =IF(A87="","",A87&" x"&C87) | K78: =IF(A87="","",ROUNDUP(F87/10,0)*10)
A79: TAXABLE AV & PRODUCTION EQUIPMENT | J79: =IF(A88="","",A88&" x"&C88) | K79: =IF(A88="","",ROUNDUP(F88/10,0)*10)
E80: =C80*D80 | F80: =IFERROR(E80*(1+VLOOKUP(I80,CategoryTable,2,FALSE)),0) | G80: ='Client Setup'!B19 | I80: AV & Production | J80: =IF(A89="","",A89&" x"&C89) | K80: =IF(A89="","",ROUNDUP(F89/10,0)*10)
E81: =C81*D81 | F81: =IFERROR(E81*(1+VLOOKUP(I81,CategoryTable,2,FALSE)),0) | G81: ='Client Setup'!B19 | I81: AV & Production | J81: =IF(A91="","",A91) | K81: =IF(A91="","",ROUNDUP(F91/10,0)*10)
E82: =C82*D82 | F82: =IFERROR(E82*(1+VLOOKUP(I82,CategoryTable,2,FALSE)),0) | G82: ='Client Setup'!B19 | I82: AV & Production | J82: =IF(A92="","",A92) | K82: =IF(A92="","",ROUNDUP(F92/10,0)*10)
E83: =C83*D83 | F83: =IFERROR(E83*(1+VLOOKUP(I83,CategoryTable,2,FALSE)),0) | G83: ='Client Setup'!B19 | I83: AV & Production | J83: =IF(A93="","",A93) | K83: =IF(A93="","",ROUNDUP(F93/10,0)*10)
E84: =C84*D84 | F84: =IFERROR(E84*(1+VLOOKUP(I84,CategoryTable,2,FALSE)),0) | G84: ='Client Setup'!B19 | I84: AV & Production | J84: =IF(A94="","",A94) | K84: =IF(A94="","",ROUNDUP(F94/10,0)*10)
E85: =C85*D85 | F85: =IFERROR(E85*(1+VLOOKUP(I85,CategoryTable,2,FALSE)),0) | G85: ='Client Setup'!B19 | I85: AV & Production | J85: =IF(A95="","",A95) | K85: =IF(A95="","",ROUNDUP(F95/10,0)*10)
E86: =C86*D86 | F86: =IFERROR(E86*(1+VLOOKUP(I86,CategoryTable,2,FALSE)),0) | G86: ='Client Setup'!B19 | I86: AV & Production | J86: AV / Production Subtotal | K86: =SUM(K71:K85)
E87: =C87*D87 | F87: =IFERROR(E87*(1+VLOOKUP(I87,CategoryTable,2,FALSE)),0) | G87: ='Client Setup'!B19 | I87: AV & Production
E88: =C88*D88 | F88: =IFERROR(E88*(1+VLOOKUP(I88,CategoryTable,2,FALSE)),0) | G88: ='Client Setup'!B19 | I88: AV & Production | J88: Tax | K88: =ROUNDUP(F100/10,0)*10
E89: =C89*D89 | F89: =IFERROR(E89*(1+VLOOKUP(I89,CategoryTable,2,FALSE)),0) | G89: ='Client Setup'!B19 | I89: AV & Production
A90: NON-TAXABLE AV FEES & LABOR | J90: TOTAL | K90: =K29+K68+K86+K88
A91: AV Tech Labor | E91: =D91 | F91: =IFERROR(E91*(1+VLOOKUP(I91,CategoryTable,2,FALSE)),0) | G91: 0 | I91: Staffing & Labor
A92: Delivery / Setup | E92: =D92 | F92: =IFERROR(E92*(1+VLOOKUP(I92,CategoryTable,2,FALSE)),0) | G92: 0 | I92: Staffing & Labor
A93: Strike / Removal | E93: =D93 | F93: =IFERROR(E93*(1+VLOOKUP(I93,CategoryTable,2,FALSE)),0) | G93: 0 | I93: Staffing & Labor
E94: =D94 | F94: =IFERROR(E94*(1+VLOOKUP(I94,CategoryTable,2,FALSE)),0) | G94: 0 | I94: Staffing & Labor
E95: =D95 | F95: =IFERROR(E95*(1+VLOOKUP(I95,CategoryTable,2,FALSE)),0) | G95: 0 | I95: Staffing & Labor
A96: AV / PRODUCTION SUBTOTAL | E96: =SUM(E80:E89)+SUM(E91:E95) | F96: =SUM(F80:F89)+SUM(F91:F95)
A98: ESTIMATE SUMMARY
A99: Taxable Product Subtotal | E99: =SUM(E16:E25)+SUM(E35:E42)+SUM(E44:E51)+SUM(E53:E60)+SUM(E62:E67)+SUM(E80:E89) | F99: =SUM(F16:F25)+SUM(F35:F42)+SUM(F44:F51)+SUM(F53:F60)+SUM(F62:F67)+SUM(F80:F89)
A100: Sales Tax | E100: =IFERROR(E99*'Client Setup'!B19,0) | F100: =IFERROR(F99*'Client Setup'!B19,0)
A101: Non-Taxable Fees Subtotal | E101: =SUM(E27:E29)+SUM(E69:E74)+SUM(E91:E95) | F101: =SUM(F27:F29)+SUM(F69:F74)+SUM(F91:F95)
A102: CC Processing Fee | E102: =F102 | F102: =IFERROR((F99+F100+F101)*'Client Setup'!C35,0)
A103: Third-Party Commission | E103: =F103 | F103: =IFERROR((F99+F100+F101)*'Client Setup'!C36,0)
...
